inventario.py
inventario-1.0.0.dist-info/LICENSE
inventario-1.0.0.dist-info/METADATA
inventario-1.0.0.dist-info/WHEEL
inventario-1.0.0.dist-info/top_level.txt
inventario-1.0.0.dist-info/RECORD
