Metadata-Version: 2.1
Name: inventario
Version: 1.0.0
Summary: Inventario para equipamentos
Home-page: http://professorfelipe.000webhostapp.com/
Author: Felipe Augusto
Author-email: fasnik@gmail.com
License: UNKNOWN
Platform: UNKNOWN
Classifier: Programming Language :: Python :: 3
Classifier: License :: OSI Approved :: MIT License
Requires-Python: >=3.6
